wexample_wex_addon_dev_css-0.0.17.dist-info/METADATA
wexample_wex_addon_dev_css-0.0.17.dist-info/WHEEL
wexample_wex_addon_dev_css-0.0.17.dist-info/entry_points.txt
wexample_wex_addon_dev_css/__init__.py
wexample_wex_addon_dev_css/css_addon_manager.py
wexample_wex_addon_dev_css/py.typed
wexample_wex_addon_dev_css-0.0.17.dist-info/RECORD
